CLASV/MANIFEST.in
CLASV/README.md
CLASV/VERSION
CLASV/__init__.py
CLASV/benchmark_clasv.py
CLASV/cli.py
CLASV/core.py
CLASV/install_nextclade.py
CLASV/install_seqkit.py
CLASV/pipeline.py
CLASV/predflow_updated.png
CLASV/predict_lineage.smk
CLASV/requirements.txt
CLASV/setup.py
CLASV/CLASV.egg-info/PKG-INFO
CLASV/CLASV.egg-info/SOURCES.txt
CLASV/CLASV.egg-info/dependency_links.txt
CLASV/CLASV.egg-info/entry_points.txt
CLASV/CLASV.egg-info/requires.txt
CLASV/CLASV.egg-info/top_level.txt
CLASV/__pycache__/__init__.cpython-310.pyc
CLASV/__pycache__/__init__.cpython-311.pyc
CLASV/__pycache__/__init__.cpython-312.pyc
CLASV/__pycache__/__init__.cpython-313.pyc
CLASV/__pycache__/__init__.cpython-38.pyc
CLASV/__pycache__/__init__.cpython-39.pyc
CLASV/__pycache__/cli.cpython-310.pyc
CLASV/__pycache__/cli.cpython-311.pyc
CLASV/__pycache__/cli.cpython-312.pyc
CLASV/__pycache__/cli.cpython-313.pyc
CLASV/__pycache__/cli.cpython-38.pyc
CLASV/__pycache__/cli.cpython-39.pyc
CLASV/__pycache__/core.cpython-310.pyc
CLASV/__pycache__/core.cpython-311.pyc
CLASV/__pycache__/core.cpython-312.pyc
CLASV/__pycache__/core.cpython-313.pyc
CLASV/__pycache__/core.cpython-38.pyc
CLASV/__pycache__/core.cpython-39.pyc
CLASV/__pycache__/install_nextclade.cpython-310.pyc
CLASV/__pycache__/install_nextclade.cpython-311.pyc
CLASV/__pycache__/install_nextclade.cpython-312.pyc
CLASV/__pycache__/install_nextclade.cpython-313.pyc
CLASV/__pycache__/install_nextclade.cpython-38.pyc
CLASV/__pycache__/install_nextclade.cpython-39.pyc
CLASV/__pycache__/install_seqkit.cpython-310.pyc
CLASV/__pycache__/install_seqkit.cpython-311.pyc
CLASV/__pycache__/install_seqkit.cpython-312.pyc
CLASV/__pycache__/install_seqkit.cpython-313.pyc
CLASV/__pycache__/install_seqkit.cpython-38.pyc
CLASV/__pycache__/install_seqkit.cpython-39.pyc
CLASV/__pycache__/pipeline.cpython-310.pyc
CLASV/__pycache__/pipeline.cpython-311.pyc
CLASV/__pycache__/pipeline.cpython-312.pyc
CLASV/__pycache__/pipeline.cpython-313.pyc
CLASV/__pycache__/pipeline.cpython-38.pyc
CLASV/__pycache__/pipeline.cpython-39.pyc
CLASV/config/NC_004296.fasta
CLASV/config/RF_LASV_lineage_n100_aa.joblib
CLASV/config/config.yaml
CLASV/raw_data/Adesina_et_al_2023_EMI.csv
clasv-1.0.6.dist-info/licenses/LICENSE
clasv-1.0.6.dist-info/METADATA
clasv-1.0.6.dist-info/WHEEL
clasv-1.0.6.dist-info/entry_points.txt
clasv-1.0.6.dist-info/top_level.txt
clasv-1.0.6.dist-info/RECORD
