Metadata-Version: 2.4
Name: CLASV
Version: 1.0.6
Summary: CLASV is a pipeline designed for rapidly predicting Lassa virus lineages using a Random Forest model.
Home-page: https://github.com/JoiRichi/CLASV/commits?author=JoiRichi
Author: Richard Daodu, Ebenezer Awotoro, Jens-Uwe Ulrich, Denise Kühnert
Author-email: lordrichado@gmail.com
Classifier: Programming Language :: Python :: 3.8
Classifier: Programming Language :: Python :: 3.9
Classifier: Programming Language :: Python :: 3.10
Classifier: Programming Language :: Python :: 3.11
Classifier: Programming Language :: Python :: 3.12
Classifier: Programming Language :: Python :: 3.13
Classifier: License :: OSI Approved :: MIT License
Classifier: Operating System :: OS Independent
Requires-Python: >=3.7,<3.14
License-File: LICENSE
Requires-Dist: numpy<1.20,>=1.18; python_version < "3.8"
Requires-Dist: numpy<1.24,>=1.21; python_version >= "3.8" and python_version < "3.12"
Requires-Dist: numpy>=1.26; python_version >= "3.12"
Requires-Dist: biopython<1.79; python_version < "3.7"
Requires-Dist: biopython<1.81; python_version >= "3.7" and python_version < "3.8"
Requires-Dist: biopython<1.85; python_version >= "3.8" and python_version < "3.13"
Requires-Dist: biopython>=1.85; python_version >= "3.13"
Requires-Dist: pandas<1.2,>=1.1; python_version < "3.7"
Requires-Dist: pandas<1.5,>=1.3; python_version >= "3.7" and python_version < "3.8"
Requires-Dist: pandas<2.0,>=1.5; python_version >= "3.8" and python_version < "3.9"
Requires-Dist: pandas<2.3,>=2.1; python_version >= "3.9"
Requires-Dist: scipy<1.6; python_version < "3.7"
Requires-Dist: scipy<1.8; python_version >= "3.7" and python_version < "3.8"
Requires-Dist: scipy<1.11; python_version >= "3.8" and python_version < "3.10"
Requires-Dist: scipy<1.15,>=1.11; python_version >= "3.10" and python_version < "3.12"
Requires-Dist: scipy>=1.14; python_version >= "3.12"
Requires-Dist: scikit-learn<0.25; python_version < "3.7"
Requires-Dist: scikit-learn<1.2; python_version >= "3.7" and python_version < "3.8"
Requires-Dist: scikit-learn<1.4; python_version >= "3.8" and python_version < "3.11"
Requires-Dist: scikit-learn>=1.4; python_version >= "3.11"
Requires-Dist: plotly<5; python_version < "3.7"
Requires-Dist: plotly<6,>=5; python_version >= "3.7"
Requires-Dist: matplotlib<3.4; python_version < "3.7"
Requires-Dist: matplotlib<3.6; python_version >= "3.7" and python_version < "3.8"
Requires-Dist: matplotlib<3.8; python_version >= "3.8" and python_version < "3.10"
Requires-Dist: matplotlib<3.10; python_version >= "3.10"
Requires-Dist: PyYAML<6; python_version < "3.7"
Requires-Dist: PyYAML>=6; python_version >= "3.7"
Requires-Dist: requests<2.28; python_version < "3.7"
Requires-Dist: requests>=2.31; python_version >= "3.7"
Requires-Dist: urllib3<2; python_version < "3.8"
Requires-Dist: urllib3>=2; python_version >= "3.8"
Requires-Dist: joblib<1.2,>=1.0; python_version < "3.7"
Requires-Dist: joblib>=1.2; python_version >= "3.7"
Requires-Dist: snakemake<6; python_version < "3.8"
Requires-Dist: snakemake<9,>=7; python_version >= "3.8"
Requires-Dist: PuLP<2.8,>=2.6
Requires-Dist: importlib_metadata<5; python_version < "3.8"
Requires-Dist: zipp<3.0; python_version < "3.7"
Requires-Dist: typing-extensions>=4.1; python_version < "3.8"
Requires-Dist: dataclasses; python_version < "3.7"
Dynamic: author
Dynamic: author-email
Dynamic: classifier
Dynamic: description
Dynamic: description-content-type
Dynamic: home-page
Dynamic: license-file
Dynamic: requires-dist
Dynamic: requires-python
Dynamic: summary
